antidotes/__init__.py
antidotes/assistance.pyw
antidotes/interactor.py
antidotes/core/__init__.py
antidotes/core/__init__py
antidotes/core/anti_saycheese.py
antidotes/core/anti_shellphish.py
antidotes/core/anti_whatsphish.py
antidotes/core/anti_zshadow.py
antidotes/core/connection_manager.py
antidotes/core/scanner.py
antidotes-0.1.0.dist-info/entry_points.txt
antidotes-0.1.0.dist-info/WHEEL
antidotes-0.1.0.dist-info/METADATA
antidotes-0.1.0.dist-info/RECORD
