Metadata-Version: 2.1
Name: antidotes
Version: 0.1.0
Summary: antidote - A Script kiddies buster tool
Home-page: https://github.com/StrinTH/Antidote
License: UNKNOWN
Author: 0x0is1
Author-email: 0x0is1@protonmail.com
Requires-Python: >=3.7
Classifier: Intended Audience :: End Users/Desktop
Classifier: License :: OSI Approved :: MIT License
Classifier: Programming Language :: Python :: 3
Requires-Dist: beautifulsoup4
Requires-Dist: requests
Requires-Dist: Pillow
Requires-Dist: notify2
Requires-Dist: flit ; extra == "dev"
Provides-Extra: dev
